rustpy_tools-0.2.1.dist-info/METADATA
rustpy_tools-0.2.1.dist-info/WHEEL
rustpy_tools.cpython-36m-darwin.so
rustpy_tools-0.2.1.dist-info/RECORD
