Metadata-Version: 2.1
Name: rustpy-tools
Version: 0.2.1
Summary: A useful tool Python module implement in rust-lang.
Home-Page: https://github.com/leohowell/rustpy-tools
Author: leohowell.com@gmail.com
Author-Email: leohowell.com@gmail.com
License: BSD-2-Clause
